ucg_client/.gitignore
ucg_client/__init__.py
ucg_client/_version.py
ucg_client/generator_pb2.py
ucg_client/generator_pb2.pyi
ucg_client/generator_pb2_grpc.py
ucg_client/__pycache__/__init__.cpython-39.pyc
ucg_client-0.0.51.dist-info/LICENSE
ucg_client-0.0.51.dist-info/METADATA
ucg_client-0.0.51.dist-info/WHEEL
ucg_client-0.0.51.dist-info/top_level.txt
ucg_client-0.0.51.dist-info/RECORD
